time_me/__data__.py
time_me/__init__.py
time_me/coach.py
time_me/runner.py
time_me/timer.py
time_me-0.2.0.dist-info/METADATA
time_me-0.2.0.dist-info/RECORD
time_me-0.2.0.dist-info/WHEEL
time_me-0.2.0.dist-info/top_level.txt
