Metadata-Version: 2.1
Name: time-me
Version: 0.2.0
Summary: UNKNOWN
Home-page: https://github.com/bentheiii/time_me
Author: ben avrahami
License: UNKNOWN
Platform: UNKNOWN
Requires-Python: >=3.7.0
Provides-Extra: bar plots
Provides-Extra: bar plots
Requires-Dist: matplotlib; extra == 'bar plots'
